eurofiber_package/__init__.py
eurofiber_package/address_functions.py
eurofiber_package/cocon_functions.py
eurofiber_package/dataset_functions.py
eurofiber_package/datasets-NB1627.py
eurofiber_package/datasets.py
eurofiber_package/enrichment_functions.py
eurofiber_package/general_functions.py
eurofiber_package/geographical_functions.py
eurofiber_package/myfunctions.py
eurofiber_package/scrapers.py
eurofiber_package-0.1.32.dist-info/METADATA
eurofiber_package-0.1.32.dist-info/PKG-INFO-NB1627
eurofiber_package-0.1.32.dist-info/WHEEL
eurofiber_package-0.1.32.dist-info/top_level.txt
eurofiber_package-0.1.32.dist-info/RECORD
