Metadata-Version: 2.1
Name: eurofiber-package
Version: 0.1.32
Summary: My first Python library
Home-page: UNKNOWN
Author: Me
License: MIT
Platform: UNKNOWN
